TibblingAI/__init__.py
TibblingAI/tibbling_RegAI.py
TibblingAI/tibbling_SegAI.py
TibblingAI/tibbling_preprocess.py
TibblingAI/tibbling_utils.py
TibblingAI/utils_Zurich_Dev.py
tibblingai-1.1.0.dist-info/METADATA
tibblingai-1.1.0.dist-info/WHEEL
tibblingai-1.1.0.dist-info/top_level.txt
tibblingai-1.1.0.dist-info/RECORD
