Metadata-Version: 2.4
Name: TibblingAI
Version: 1.1.0
Summary: TibblingAI Codebase
Author: Taha
Author-email: taharazzaq091@gmail.com
Classifier: Programming Language :: Python :: 3
Classifier: License :: OSI Approved :: MIT License
Classifier: Operating System :: OS Independent
Requires-Dist: numpy
Requires-Dist: pynrrd
Requires-Dist: opencv-python
Requires-Dist: pandas
Requires-Dist: patsy
Requires-Dist: pillow
Requires-Dist: plotly
Requires-Dist: natsort
Requires-Dist: matplotlib
Requires-Dist: antspyx
Dynamic: author
Dynamic: author-email
Dynamic: classifier
Dynamic: description-content-type
Dynamic: requires-dist
Dynamic: summary
